signaturesimulator/__init__.py
signaturesimulator/activemicro_rt.py
signaturesimulator/atmospheric_rt.py
signaturesimulator/backscatter.py
signaturesimulator/core.py
signaturesimulator/jules.py
signaturesimulator/opticalcanopy_rt.py
signaturesimulator/plotting_utils.py
signaturesimulator/satellite_geometry.py
signaturesimulator/site.nml
signaturesimulator/spectra.py
signaturesimulator/state_vector.py
signaturesimulator/data/geometries/s1_example.csv
signaturesimulator/data/geometries/s1_example_const.csv
signaturesimulator/data/geometries/s2_example.csv
signaturesimulator/data/geometries/s2_example_const.csv
signaturesimulator/data/jules/example_nml/ancillaries.nml
signaturesimulator/data/jules/example_nml/crop_params.nml
signaturesimulator/data/jules/example_nml/drive.nml
signaturesimulator/data/jules/example_nml/fire.nml
signaturesimulator/data/jules/example_nml/imogen.nml
signaturesimulator/data/jules/example_nml/initial_conditions.nml
signaturesimulator/data/jules/example_nml/jules_hydrology.nml
signaturesimulator/data/jules/example_nml/jules_radiation.nml
signaturesimulator/data/jules/example_nml/jules_rivers.nml
signaturesimulator/data/jules/example_nml/jules_snow.nml
signaturesimulator/data/jules/example_nml/jules_soil.nml
signaturesimulator/data/jules/example_nml/jules_soil_biogeochem.nml
signaturesimulator/data/jules/example_nml/jules_surface.nml
signaturesimulator/data/jules/example_nml/jules_surface_types.nml
signaturesimulator/data/jules/example_nml/jules_vegetation.nml
signaturesimulator/data/jules/example_nml/model_grid.nml
signaturesimulator/data/jules/example_nml/nveg_params.nml
signaturesimulator/data/jules/example_nml/output.nml
signaturesimulator/data/jules/example_nml/pft_params.nml
signaturesimulator/data/jules/example_nml/prescribed_data.nml
signaturesimulator/data/jules/example_nml/timesteps.nml
signaturesimulator/data/jules/example_nml/triffid_params.nml
signaturesimulator-0.3.4.dist-info/DESCRIPTION.rst
signaturesimulator-0.3.4.dist-info/METADATA
signaturesimulator-0.3.4.dist-info/RECORD
signaturesimulator-0.3.4.dist-info/WHEEL
signaturesimulator-0.3.4.dist-info/metadata.json
signaturesimulator-0.3.4.dist-info/top_level.txt
