Metadata-Version: 2.0
Name: signaturesimulator
Version: 0.3.4
Summary: A Python package that simulates satellite data from passive optical and active microwave sensors based on land surface biogeophysical state variables (leaf area index, canopy height and soil moisture) and viewing geometries and times.
Home-page: https://github.com/pyearthsci/signaturesimulator
Author: T. Quaife and E. Pinnington
Author-email: e.pinnington@reading.ac.uk
License: UNKNOWN
Keywords: satellite earth science land surface passive optical active microwave sentinel
Platform: UNKNOWN
Requires-Dist: f90nml
Requires-Dist: matplotlib (<3,>=1.4.3)
Requires-Dist: mock
Requires-Dist: netCDF4
Requires-Dist: numpy
Requires-Dist: pyorbital
Requires-Dist: scipy
